pytest_patches.py
pytest_patches-0.0.3.dist-info/LICENSE
pytest_patches-0.0.3.dist-info/METADATA
pytest_patches-0.0.3.dist-info/WHEEL
pytest_patches-0.0.3.dist-info/entry_points.txt
pytest_patches-0.0.3.dist-info/top_level.txt
pytest_patches-0.0.3.dist-info/RECORD
